dmem.v
`include "def.h"
module dmem (
 input clk,
 input [15:0] a,
 output [`DATA_W-1:0] rd,
 input [`DATA_W-1:0] wd,
 input  we);

	reg [`DATA_W-1:0] mem[0:`DEPTH-1];

	assign rd = mem[a];

	always @(posedge clk)  begin
		if(we) mem[a] <= wd;
	end
	initial
      begin
           $readmemh("dmem.dat", mem);
    end


endmodule

imem.v
`include "def.h"
module imem (
 input [15:0] a,
 output [`DATA_W-1:0] rd);

	reg [`DATA_W-1:0] mem[0:`DEPTH-1];

	assign rd = mem[a];

	initial
      begin
           $readmemb("imem.dat", mem);
    end


endmodule

alu.v
`include "def.h"

module alu (
  input [`DATA_W-1:0] a, b, 
  input [2:0] s, 
  input ext,addcom,
  output [`DATA_W-1:0] y );
  wire [4:0] shamt;
  wire signed [31:0] sa, sb, sy, slt;
  wire [31:0] sltu;
  wire [31:0] yy;
  assign sa = $signed(a);
  assign sb = $signed(b);
  assign shamt = b[4:0];
  assign sy = sa >>> shamt;
  assign sltu = a <b ? 1:0;
  assign slt = sa <sb ? 1:0;
  assign y = addcom ?  a+b: yy;
  assign yy = s==`ALU_ADD & ext ? a-b:
  			 s==`ALU_ADD & ~ext ? a+b:
             s==`ALU_XOR ? a ^ b:
             s==`ALU_OR ? a | b:
             s==`ALU_AND ? a & b:
             s==`ALU_SLT ? slt:
             s==`ALU_SLTU ? sltu:
             s==`ALU_SLL ? a << shamt:
             s==`ALU_SRL & ~ext ? a >> shamt:
             s==`ALU_SRL & ext ? sy: 0;
endmodule

rfile.v
`include "def.h"
module rfile (
 input clk,
 input [`REG_W-1:0] a1, a2, a3,
 output [`DATA_W-1:0] rd1, rd2,
 input [`DATA_W-1:0] wd3,
 input we3);

	reg [`DATA_W-1:0] rf[0:`REG-1];

	assign rd1 = |a1 == 0 ? 0: rf[a1];
	assign rd2 = |a2 == 0 ? 0: rf[a2];

	always @(negedge clk) 
		if(we3) rf[a3] <= wd3;

endmodule

rv32i.v
`include "def.h"
module rv32i (
    input clk,
    rst_n,
    input [`DATA_W-1:0] instr,
    input [`DATA_W-1:0] readdata,
    output reg [`DATA_W-1:0] pc,
    output [`DATA_W-1:0] adrdata,
    output [`DATA_W-1:0] writedata,
    output we,
    output ecall
);

  /*  Instruction Fetch Stage */
  reg [`DATA_W-1:0] pcplus4D;
  wire [`DATA_W-1:0] pcplus4;
  reg [`DATA_W-1:0] pcBranchMissed;
  reg [`DATA_W-1:0] instrD;
  wire stall;
  wire btakenD;
  wire bra_op;
  assign pcplus4 = pc + 4;

  // static branch prediction
  wire pre_bra_op;
  wire [`DATA_W-1:0] pcbranch;
  wire branchMiss;

  reg [1:0] bra_history[0:15];
  wire [3:0] bra_history_address;
  reg [3:0] bra_history_addressD;

  wire [12:0] imm_bF;
  wire [2:0] funct3F;
  wire [6:0] funct7F;
  wire [`OPCODE_W-1:0] opcodeF;
  wire [`REG_W-1:0] rs1F, rs2F, rdF;
  wire [19:0] sextF;
  assign {funct7F, rs2F, rs1F, funct3F, rdF, opcodeF} = instr;
  assign sextF = {20{instr[31]}};
  assign imm_bF = {funct7F[6], rdF[0], funct7F[5:0], rdF[4:1], 1'b0};

  assign pre_bra_op = (opcodeF == `OP_BRA);
  assign pcbranch = pcplus4 + {sextF[18:0], imm_bF};
  assign bra_history_address = pc[5:2];
  wire bra_history_now;
  assign bra_history_now = bra_history[bra_history_address];


  always @(posedge clk or negedge rst_n) begin
    if (!rst_n) instrD <= 0;
    else if (!stall & branchMiss & bra_op) instrD <= `NOP;
    else if (!stall) instrD <= instr;
  end

  integer i;
  always @(posedge clk or negedge rst_n) begin
    if (!rst_n) begin
      pc <= 0;
      pcBranchMissed <= 0;

      for (i = 0; i < 16; i = i + 1) begin
        bra_history[i] <= 2'b10;
      end
      bra_history_addressD <= 0;
    end else if (!stall & branchMiss & bra_op) pc <= pcBranchMissed;
    else if (!stall & pre_bra_op & bra_history[bra_history_address][1]) begin
      pc <= pcbranch;
      pcBranchMissed <= pcplus4;
      bra_history_addressD <= bra_history_address;
    end else if (!stall & pre_bra_op & !bra_history[bra_history_address][1]) begin
      pc <= pcplus4;
      pcBranchMissed <= pcbranch;
      bra_history_addressD <= bra_history_address;
    end else if (!stall & branchMiss & bra_op) pc <= pcBranchMissed;
    else if (!stall) pc <= pcplus4;

    if (bra_op) begin
      if (btakenD) begin
        if (bra_history[bra_history_addressD] != 2'b11)
          bra_history[bra_history_addressD] <= bra_history[bra_history_addressD] + 1;
      end else if (bra_history[bra_history_addressD] != 2'b00)
        bra_history[bra_history_addressD] <= bra_history[bra_history_addressD] - 1;
    end
  end

  always @(posedge clk or negedge rst_n) begin
    if (!rst_n) pcplus4D <= 0;
    else if (!stall) pcplus4D <= pcplus4;
  end



  /*  Instruction Decorder Stage */

  wire addcom;
  wire [2:0] funct3;
  wire [6:0] funct7;
  wire [`REG_W-1:0] rs1, rs2, rd;
  wire [`DATA_W-1:0] reg1, reg2, reg1f, reg2f;
  wire [`OPCODE_W-1:0] opcode;
  wire [ `SHAMT_W-1:0] shamt;
  wire [`OPCODE_W-1:0] func;
  wire [11:0] imm_i, imm_s;
  wire [12:0] imm_b;
  wire [20:0] imm_j, imm_u;
  wire rwe;
  wire alu_op, imm_op;
  wire sw_op, beq_op, bne_op, blt_op, bge_op, bltu_op, bgeu_op, lw_op;
  wire slt_op, ecall_op;
  wire lui_op;
  wire ext;
  wire signed [31:0] sreg1, sreg2;
  wire [19:0] sext;
  wire [`DATA_W-1:0] imm;

  // pipeline registers
  reg [`DATA_W-1:0] immE, reg1E, reg2E;
  wire [`DATA_W-1:0] resultdata;
  reg [`REG_W-1:0] rdE, rdW;
  reg [2:0] funct3E;
  reg extE, sw_opE, lw_opE, lw_opM, lui_opE, ecall_opE, rweE, rweM, addcomE;
  reg [`REG_W-1:0] rdM;
  reg rweW, alu_opE;
  reg [`REG_W-1:0] rs1E, rs2E;
  wire lwstall, branchstall;
  reg [`DATA_W-1:0] resultM;

  assign sreg1 = $signed(reg1f);
  assign sreg2 = $signed(reg2f);
  assign {funct7, rs2, rs1, funct3, rd, opcode} = instrD;
  assign sext = {20{instrD[31]}};
  assign imm_i = {funct7, rs2};
  assign imm_s = {funct7, rd};
  assign imm_b = {funct7[6], rd[0], funct7[5:0], rd[4:1], 1'b0};
  assign imm_j = {instrD[31], instrD[19:12], instrD[20], instrD[30:21], 1'b0};
  assign imm_u = instrD[31:12];
  // Decorder
  assign sw_op = (opcode == `OP_STORE) & (funct3 == 3'b010);
  assign lw_op = (opcode == `OP_LOAD) & (funct3 == 3'b010);
  assign alu_op = (opcode == `OP_REG);
  assign imm_op = (opcode == `OP_IMM);
  assign bra_op = (opcode == `OP_BRA);
  assign lui_op = (opcode == `OP_LUI);
  assign beq_op = bra_op & (funct3 == 3'b000);
  assign bne_op = bra_op & (funct3 == 3'b001);
  assign blt_op = bra_op & (funct3 == 3'b100);
  assign bge_op = bra_op & (funct3 == 3'b101);
  assign bltu_op = bra_op & (funct3 == 3'b110);
  assign bgeu_op = bra_op & (funct3 == 3'b111);
  assign ecall_op = (opcode == `OP_SPE) & (funct3 == 3'b000);
  assign ext = alu_op & funct7[5];

  assign	imm = imm_op | lw_op ? {sext, imm_i}: 
				sw_op ? {sext, imm_s}: 
				lui_op ? {imm_u,12'b0}: {sext[10:0], imm_j};

  assign rwe = lw_op | alu_op | imm_op | lui_op;
  assign addcom = (lw_op | sw_op);

  rfile rfile_1 (
      .clk(clk),
      .rd1(reg1),
      .a1 (rs1),
      .rd2(reg2),
      .a2 (rs2),
      .wd3(resultdata),
      .a3 (rdW),
      .we3(rweW)
  );
  // Stall
  assign lwstall = ((rs1 == rdE) | ((rs2 == rdE) & !imm_op)) & lw_opE;
  assign branchstall =  (bra_op & rweE & (rs1 == rdE | rs2 == rdE)) |
      (bra_op & lw_opM & (rs1 == rdM | rs2 == rdM));
  assign stall = lwstall | branchstall;
  assign branchMiss = btakenD != bra_history[bra_history_addressD][1];

  // Forwarding;
  assign reg1f = (rs1 != 0) & (rs1 == rdM) & rweM ? resultM : reg1;
  assign reg2f = (rs2 != 0) & (rs2 == rdM) & rweM ? resultM : reg2;

  // Branch
  assign btakenD = beq_op & (reg1f == reg2f) | bne_op & (reg1f != reg2f) |
		blt_op & (sreg1<sreg2)  | bge_op & (sreg1>=sreg2)  |
		bltu_op & (reg1f<reg2f)  | bgeu_op & (reg1f>=reg2f);
  // assign pcbranchD = pcplus4D + {sext[18:0],imm_b};

  always @(posedge clk or negedge rst_n) begin
    if (!rst_n) begin
      reg1E <= 0;
      reg2E <= 0;
      rdE <= 0;
      rs1E <= 0;
      rs2E <= 0;
      funct3E <= 0;
      sw_opE <= 0;
      lw_opE <= 0;
      ecall_opE <= 0;
      lui_opE <= 0;
      alu_opE <= 0;
      rweE <= 0;
      addcomE <= 0;
      extE <= 0;
      immE <= 0;
    end else if (stall) begin
      //		rs1E<=0; rs2E<=0; rdE<=0; 
      sw_opE <= 0;
      rweE   <= 0;
      lw_opE <= 0;
    end else begin
      reg1E <= reg1f;
      reg2E <= reg2f;
      rdE <= rd;
      rs1E <= rs1;
      rs2E <= rs2;
      funct3E <= funct3;
      sw_opE <= sw_op;
      lw_opE <= lw_op;
      ecall_opE <= ecall_op;
      lui_opE <= lui_op;
      alu_opE <= alu_op;
      rweE <= rwe;
      addcomE <= addcom;
      extE <= ext;
      immE <= imm;
    end
  end

  /*  Execution Stage */
  wire [`DATA_W-1:0] srca, srcb, alub, result, aluresult;
  reg [`DATA_W-1:0] alubM;
  reg sw_opM, ecall_opM;
  wire [`DATA_W-1:0] fdata;
  reg  [`DATA_W-1:0] fdataW;
  // assign srca = reg1E;
  // assign srcb = alu_opE? reg2E: immE;
  assign result = lui_opE ? immE : aluresult;
  // Forwarding
  assign srca = rweM & rs1E!=0 & rdM == rs1E ? resultM:
				rweW & rs1E!=0 & rdW == rs1E ? fdataW: reg1E;
  assign srcb = alu_opE ? alub : immE;
  assign alub = rweM & rs2E!=0 & rdM == rs2E ? resultM:
				rweW & rs2E!=0 & rdW == rs2E ? fdataW: reg2E;

  alu alu_1 (
      .a(srca),
      .b(srcb),
      .s(funct3E),
      .ext(extE),
      .addcom(addcomE),
      .y(aluresult)
  );

  always @(posedge clk or negedge rst_n) begin
    if (!rst_n) begin
      resultM <= 0;
      alubM <= 0;
      rdM <= 0;
      rweM <= 0;
      sw_opM <= 0;
      lw_opM <= 0;
      ecall_opM <= 0;
    end else begin
      resultM <= result;
      alubM <= alub;
      rdM <= rdE;
      rweM <= rweE;
      sw_opM <= sw_opE;
      lw_opM <= lw_opE;
      ecall_opM <= ecall_opE;
    end
  end

  /*  Memory Access Stage */
  reg lw_opW, ecall_opW;
  reg [`DATA_W-1:0] resultW;
  reg [`DATA_W-1:0] readdataW;
  assign we = sw_opM;
  assign adrdata = resultM;
  assign writedata = alubM;
  assign fdata = lw_opM ? readdata : resultM;

  always @(posedge clk or negedge rst_n) begin
    if (!rst_n) begin
      lw_opW <= 0;
      ecall_opW <= 0;
      rdW <= 0;
      rweW <= 0;
      fdataW <= 0;
      resultW <= 0;
      readdataW <= 0;
    end else begin
      lw_opW <= lw_opM;
      ecall_opW <= ecall_opM;
      rdW <= rdM;
      rweW <= rweM;
      readdataW <= readdata;
      fdataW <= fdata;
      resultW <= resultM;
    end
  end
  /*  Write back Stage */
  assign ecall = ecall_opW;
  assign resultdata = lw_opW ? readdataW : resultW;
endmodule

test_rv32i.v
/* test bench */
`timescale 1ns/1ps
`include "def.h"
module test_rv32i;
parameter STEP = 10;
   reg clk, rst_n;
   wire [`DATA_W-1:0] ddataout, ddatain ;
   wire [`DATA_W-1:0] iaddr;
   wire [`DATA_W-1:0] daddr;
   wire [`DATA_W-1:0] idata;
   wire we, ecall_op;
   reg [31:0] count, sc_lw, sc_bb, sc_ab;
   integer FP;
   integer i;
  
   always #(STEP/2) begin
            clk <= ~clk;
   end

   rv32i rv32i_1(.clk(clk), .rst_n(rst_n), .instr(idata),
               .readdata(ddatain), .pc(iaddr), .adrdata(daddr),
               .writedata(ddataout), .we(we), .ecall(ecall_op) );
  imem  imem_1(.a(iaddr[17:2]), .rd(idata) );
  dmem  dmem_1(.clk(clk), .a(daddr[17:2]), .rd(ddatain), 
  					.wd(ddataout), .we(we) );

   initial begin
      $dumpfile("rv32i.vcd");
      $dumpvars(0,test_rv32i);
      FP= $fopen("result.dat");
      clk <= `DISABLE;
      rst_n <= `ENABLE_N;
	  count <= 0;
	  sc_lw <= 0;
	  sc_bb <= 0;
	  sc_ab <= 0;
   #(STEP*1/4)
   #STEP
      rst_n <= `DISABLE_N;
   #(STEP*10000)
   $finish;
   end

   always @(negedge clk) begin
      $display("pc:%h/%d idatain:%h", rv32i_1.pc, rv32i_1.pc, rv32i_1.instr);
      $display("x1:%h x2:%h x3:%h x4:%h x5:%h x6:%h x7:%h", 
	rv32i_1.rfile_1.rf[1], rv32i_1.rfile_1.rf[2],
	rv32i_1.rfile_1.rf[3], rv32i_1.rfile_1.rf[4], rv32i_1.rfile_1.rf[5],
	rv32i_1.rfile_1.rf[6], rv32i_1.rfile_1.rf[7] );
`ifdef REGALL
      $display("x8:%h x9:%h x10:%h x11:%h x12:%h x13:%h x14:%h x15:%h", 
	rv32i_1.rfile_1.rf[8], rv32i_1.rfile_1.rf[9],
	rv32i_1.rfile_1.rf[10], rv32i_1.rfile_1.rf[11], rv32i_1.rfile_1.rf[12],
	rv32i_1.rfile_1.rf[13], rv32i_1.rfile_1.rf[14], rv32i_1.rfile_1.rf[15] );
      $display("x16:%h x17:%h x18:%h x19:%h x20:%h x21:%h x22:%h x23:%h", 
	rv32i_1.rfile_1.rf[16], rv32i_1.rfile_1.rf[17],
	rv32i_1.rfile_1.rf[18], rv32i_1.rfile_1.rf[19], rv32i_1.rfile_1.rf[20],
	rv32i_1.rfile_1.rf[21], rv32i_1.rfile_1.rf[22], rv32i_1.rfile_1.rf[23] );
      $display("x24:%h x25:%h x26:%h x27:%h x28:%h x29:%h x30:%h x31:%h", 
	rv32i_1.rfile_1.rf[24], rv32i_1.rfile_1.rf[25],
	rv32i_1.rfile_1.rf[26], rv32i_1.rfile_1.rf[27], rv32i_1.rfile_1.rf[28],
	rv32i_1.rfile_1.rf[29], rv32i_1.rfile_1.rf[30], rv32i_1.rfile_1.rf[31] );
`endif

    $display("dmem:%h %h %h %h", dmem_1.mem[0], dmem_1.mem[1], dmem_1.mem[2], dmem_1.mem[3] );
    $display("");
	count <= count+1;
	if(rv32i_1.lwstall) sc_lw <= sc_lw+1;
	if(rv32i_1.branchstall) sc_bb <= sc_bb+1;
	if(!rv32i_1.stall & rv32i_1.bra_op) sc_ab <= sc_ab+1;
	if(ecall_op) begin 
	   for(i=0; i<200; i=i+1)
              $fdisplay(FP,"%h", dmem_1.mem[i]);
	   $display("ecall detected: count =%d ",count); 
	   $display("stall/lw =%d",sc_lw); 
	   $display("stall/before branch =%d",sc_bb); 
	   $display("stall/after branch =%d",sc_ab); 
	$finish; end

   end 
endmodule

rv32i.vcd
$date
	Mon Jul 31 02:25:54 2023
$end
$version
	Icarus Verilog
$end
$timescale
	1ps
$end
$scope module test_rv32i $end
$var wire 1 ! we $end
$var wire 32 " idata [31:0] $end
$var wire 32 # iaddr [31:0] $end
$var wire 1 $ ecall_op $end
$var wire 32 % ddataout [31:0] $end
$var wire 32 & ddatain [31:0] $end
$var wire 32 ' daddr [31:0] $end
$var reg 1 ( clk $end
$var reg 32 ) count [31:0] $end
$var reg 1 * rst_n $end
$var reg 32 + sc_ab [31:0] $end
$var reg 32 , sc_bb [31:0] $end
$var reg 32 - sc_lw [31:0] $end
$var integer 32 . FP [31:0] $end
$var integer 32 / i [31:0] $end
$scope module dmem_1 $end
$var wire 16 0 a [15:0] $end
$var wire 1 ( clk $end
$var wire 32 1 rd [31:0] $end
$var wire 1 ! we $end
$var wire 32 2 wd [31:0] $end
$upscope $end
$scope module imem_1 $end
$var wire 16 3 a [15:0] $end
$var wire 32 4 rd [31:0] $end
$upscope $end
$scope module rv32i_1 $end
$var wire 1 5 addcom $end
$var wire 32 6 adrdata [31:0] $end
$var wire 1 7 beq_op $end
$var wire 1 8 bge_op $end
$var wire 1 9 bgeu_op $end
$var wire 1 : blt_op $end
$var wire 1 ; bltu_op $end
$var wire 1 < bne_op $end
$var wire 1 = branchMiss $end
$var wire 1 > branchstall $end
$var wire 1 ? btakenD $end
$var wire 1 ( clk $end
$var wire 1 $ ecall $end
$var wire 1 @ ecall_op $end
$var wire 1 A ext $end
$var wire 32 B instr [31:0] $end
$var wire 1 C lw_op $end
$var wire 1 D lwstall $end
$var wire 32 E readdata [31:0] $end
$var wire 1 * rst_n $end
$var wire 1 F rwe $end
$var wire 1 G stall $end
$var wire 1 H sw_op $end
$var wire 1 ! we $end
$var wire 32 I writedata [31:0] $end
$var wire 32 J sreg2 [31:0] $end
$var wire 32 K sreg1 [31:0] $end
$var wire 32 L srcb [31:0] $end
$var wire 32 M srca [31:0] $end
$var wire 20 N sextF [19:0] $end
$var wire 20 O sext [19:0] $end
$var wire 5 P rs2F [4:0] $end
$var wire 5 Q rs2 [4:0] $end
$var wire 5 R rs1F [4:0] $end
$var wire 5 S rs1 [4:0] $end
$var wire 32 T resultdata [31:0] $end
$var wire 32 U result [31:0] $end
$var wire 32 V reg2f [31:0] $end
$var wire 32 W reg2 [31:0] $end
$var wire 32 X reg1f [31:0] $end
$var wire 32 Y reg1 [31:0] $end
$var wire 5 Z rdF [4:0] $end
$var wire 5 [ rd [4:0] $end
$var wire 1 \ pre_bra_op $end
$var wire 32 ] pcplus4 [31:0] $end
$var wire 32 ^ pcbranch [31:0] $end
$var wire 7 _ opcodeF [6:0] $end
$var wire 7 ` opcode [6:0] $end
$var wire 1 a lui_op $end
$var wire 21 b imm_u [20:0] $end
$var wire 12 c imm_s [11:0] $end
$var wire 1 d imm_op $end
$var wire 21 e imm_j [20:0] $end
$var wire 12 f imm_i [11:0] $end
$var wire 13 g imm_bF [12:0] $end
$var wire 13 h imm_b [12:0] $end
$var wire 32 i imm [31:0] $end
$var wire 7 j funct7F [6:0] $end
$var wire 7 k funct7 [6:0] $end
$var wire 3 l funct3F [2:0] $end
$var wire 3 m funct3 [2:0] $end
$var wire 32 n fdata [31:0] $end
$var wire 1 o bra_op $end
$var wire 1 p bra_history_now $end
$var wire 4 q bra_history_address [3:0] $end
$var wire 32 r aluresult [31:0] $end
$var wire 32 s alub [31:0] $end
$var wire 1 t alu_op $end
$var reg 1 u addcomE $end
$var reg 1 v alu_opE $end
$var reg 32 w alubM [31:0] $end
$var reg 4 x bra_history_addressD [3:0] $end
$var reg 1 y ecall_opE $end
$var reg 1 z ecall_opM $end
$var reg 1 { ecall_opW $end
$var reg 1 | extE $end
$var reg 32 } fdataW [31:0] $end
$var reg 3 ~ funct3E [2:0] $end
$var reg 32 !" immE [31:0] $end
$var reg 32 "" instrD [31:0] $end
$var reg 1 #" lui_opE $end
$var reg 1 $" lw_opE $end
$var reg 1 %" lw_opM $end
$var reg 1 &" lw_opW $end
$var reg 32 '" pc [31:0] $end
$var reg 32 (" pcBranchMissed [31:0] $end
$var reg 32 )" pcplus4D [31:0] $end
$var reg 5 *" rdE [4:0] $end
$var reg 5 +" rdM [4:0] $end
$var reg 5 ," rdW [4:0] $end
$var reg 32 -" readdataW [31:0] $end
$var reg 32 ." reg1E [31:0] $end
$var reg 32 /" reg2E [31:0] $end
$var reg 32 0" resultM [31:0] $end
$var reg 32 1" resultW [31:0] $end
$var reg 5 2" rs1E [4:0] $end
$var reg 5 3" rs2E [4:0] $end
$var reg 1 4" rweE $end
$var reg 1 5" rweM $end
$var reg 1 6" rweW $end
$var reg 1 7" sw_opE $end
$var reg 1 8" sw_opM $end
$var integer 32 9" i [31:0] $end
$scope module alu_1 $end
$var wire 32 :" a [31:0] $end
$var wire 1 u addcom $end
$var wire 32 ;" b [31:0] $end
$var wire 1 | ext $end
$var wire 3 <" s [2:0] $end
$var wire 32 =" sa [31:0] $end
$var wire 32 >" sb [31:0] $end
$var wire 32 ?" yy [31:0] $end
$var wire 32 @" y [31:0] $end
$var wire 32 A" sy [31:0] $end
$var wire 32 B" sltu [31:0] $end
$var wire 32 C" slt [31:0] $end
$var wire 5 D" shamt [4:0] $end
$upscope $end
$scope module rfile_1 $end
$var wire 5 E" a1 [4:0] $end
$var wire 5 F" a2 [4:0] $end
$var wire 5 G" a3 [4:0] $end
$var wire 1 ( clk $end
$var wire 32 H" wd3 [31:0] $end
$var wire 1 6" we3 $end
$var wire 32 I" rd2 [31:0] $end
$var wire 32 J" rd1 [31:0] $end
$upscope $end
$upscope $end
$upscope $end
$enddefinitions $end
#0
$dumpvars
b0 J"
b0 I"
b0 H"
b0 G"
b0 F"
b0 E"
b0 D"
b0 C"
b0 B"
b0 A"
b0 @"
b0 ?"
b0 >"
b0 ="
b0 <"
b0 ;"
b0 :"
b10000 9"
08"
07"
06"
05"
04"
b0 3"
b0 2"
b0 1"
b0 0"
b0 /"
b0 ."
b0 -"
b0 ,"
b0 +"
b0 *"
b0 )"
b0 ("
b0 '"
0&"
0%"
0$"
0#"
b0 ""
b0 !"
b0 ~
b0 }
0|
0{
0z
0y
b0 x
b0 w
0v
0u
0t
b0 s
b0 r
b0 q
0p
0o
b0 n
b0 m
b0 l
b0 k
b1100 j
b0 i
b0 h
b100110000000 g
b0 f
b0 e
0d
b0 c
b0 b
0a
b0 `
b10011 _
b100110000100 ^
b100 ]
0\
b0 [
b1 Z
b0 Y
b0 X
b0 W
b0 V
b0 U
b0 T
b0 S
b0 R
b0 Q
b10000 P
b0 O
b0 N
b0 M
b0 L
b0 K
b0 J
b0 I
0H
0G
0F
b1010011 E
0D
0C
b11001000000000000000010010011 B
0A
0@
0?
0>
1=
0<
0;
0:
09
08
07
b0 6
05
b11001000000000000000010010011 4
b0 3
b0 2
b1010011 1
b0 0
bx /
b10 .
b0 -
b0 ,
b0 +
0*
b1 )
0(
b0 '
b1010011 &
b0 %
0$
b0 #
b11001000000000000000010010011 "
0!
$end
#5000
b10000 9"
1(
#10000
b10 )
0(
#12000
1*
#15000
b110010000 i
bx J
bx V
1F
b1111111100000 g
bx W
bx I"
b100110000000 h
b1111111 j
b11100 P
b1 R
b11111111111111111111 N
b110010000 e
b11001000000000000 b
b1100 k
b110010000 f
b10000 Q
b10000 F"
b110000001 c
b1 [
1d
b10011 `
b1 q
b11111111110000001000000010010011 "
b11111111110000001000000010010011 4
b11111111110000001000000010010011 B
b1 3
b11001000000000000000010010011 ""
b11111111111111111111111111101000 ^
b1000 ]
b100 #
b100 '"
b100 )"
b1010011 -"
1(
#20000
b11 )
0(
#25000
b110010000 U
b110010000 r
b110010000 @"
b110010000 ?"
b100000000010 g
b11111111111111111111111111111100 i
bx K
bx X
b10000 D"
b1 B"
b1 C"
bx s
b0 j
b0 P
b10 l
b11 Z
b11 _
b0 N
b1111111100000 h
bx Y
bx J"
b110010000 L
b110010000 ;"
b110010000 >"
b10 q
b1010000110000011 "
b1010000110000011 4
b1010000110000011 B
b10 3
b11111111111111111111 O
b100001000011111111100 e
b11111111110000001000 b
b111111100001 c
b1111111 k
b111111111100 f
b11100 Q
b11100 F"
b1 S
b1 E"
b110010000 !"
14"
b10000 3"
b1 *"
bx /"
b1000 )"
b100000001110 ^
b1100 ]
b1000 #
b1000 '"
b11111111110000001000000010010011 ""
1(
#30000
b100 )
0(
#35000
b110001100 U
b110001100 r
b110001100 @"
b0 i
b0 J
b0 V
15
1F
b1000100 g
b110001100 ?"
b0 W
b0 I"
b100000000010 h
1C
b10 j
b10101 P
b11 R
b100 Z
b10011 _
b11100 D"
b0 C"
b110010000 M
b110010000 :"
b110010000 ="
b110010000 K
b110010000 X
b0 O
b1010000000000000 e
b1010 b
b0 k
b0 f
b0 Q
b0 F"
b10 m
b11 c
b11 [
0d
b11 `
b11 q
b101010100011010001000010011 "
b101010100011010001000010011 4
b101010100011010001000010011 B
b11 3
b11111111111111111111111111111100 L
b11111111111111111111111111111100 ;"
b11111111111111111111111111111100 >"
b110010000 n
bx &
bx 1
bx E
b1100100 0
b1010000110000011 ""
b1010100 ^
b10000 ]
b1100 #
b1100 '"
b1100 )"
b11111111111111111111111111111100 !"
b11100 3"
b1 2"
bx ."
15"
b1 +"
bx %
bx 2
bx I
bx w
b110010000 '
b110010000 6
b110010000 0"
1(
#40000
b101 )
0(
#45000
b0 ?"
b10000 g
b1010101 i
bx J
bx V
05
b110001100 A"
b0 D"
b0 B"
1G
b0 s
b0 j
b0 P
b100 R
b1 l
b10000 Z
1\
b1100011 _
bx W
bx I"
b1000100 h
0C
b110010000 T
b110010000 H"
bx K
bx X
b110001100 M
b110001100 :"
b110001100 ="
b110001100 n
b100111 &
b100111 1
b100111 E
b1100011 0
b0 L
b0 ;"
b0 >"
1D
b100 q
b100001100001100011 "
b100001100001100011 4
b100001100001100011 B
b100 3
b11010100001010100 e
b101010100011010 b
b10 k
b1010101 f
b10101 Q
b10101 F"
b11 S
b11 E"
b1000100 c
b100 [
1d
b10011 `
b110010000 1"
b110010000 }
bx -"
16"
b1 ,"
b1 G"
b110001100 '
b110001100 6
b110001100 0"
b0 !"
1u
1$"
b10 ~
b10 <"
b0 3"
b11 *"
b0 /"
b110010000 ."
b10000 )"
b100100 ^
b10100 ]
b10000 #
b10000 '"
b101010100011010001000010011 ""
1(
#50000
b1 -
b110 )
0(
#55000
b110001100 K
b110001100 X
0G
0D
b100111 n
b110001100 T
b110001100 H"
0$"
04"
1%"
b11 +"
b0 %
b0 2
b0 I
b0 w
b110001100 1"
b110001100 }
b100111 -"
1(
#60000
b111 )
0(
#65000
b1 ?"
x=
x?
b1 B"
b1 C"
1G
b100111 M
b100111 :"
b100111 ="
1>
b100100 g
b100001000000000000 i
b0 J
b0 V
0F
bx K
bx X
b0 A"
b10101 D"
b1 U
bx s
b1 j
b11100 P
b11 R
b10 l
b100 Z
0\
b10011 _
b0 W
b0 I"
b10000 h
1<
b100111 T
b100111 H"
b110001100 n
b1010101 L
b1010101 ;"
b1010101 >"
b1 r
b1 @"
b1001 q
b11110000011010001000010011 "
b11110000011010001000010011 4
b11110000011010001000010011 B
b1001 3
b100001000000000000 e
b100001 b
b0 k
b0 f
b0 Q
b0 F"
b100 S
b100 E"
b1 m
b10000 c
b10000 [
0d
1o
b1100011 `
b100111 }
b11 ,"
b11 G"
1&"
0%"
05"
b1010101 !"
0u
14"
b10101 3"
b11 2"
b100 *"
bx /"
b110001100 ."
b10100 )"
b100 x
b10100 ("
b1001100 ^
b101000 ]
b100100 #
b100100 '"
b100001100001100011 ""
1(
#70000
b1 ,
b1000 )
0(
#75000
b0 U
b0 r
b0 @"
1=
b0 ?"
1?
0G
0>
b0 B"
b0 C"
b1 K
b1 X
b110001100 M
b110001100 :"
b110001100 ="
b1 n
b1010011 &
b1010011 1
b1010011 E
b0 0
b110001100 T
b110001100 H"
04"
15"
b100 +"
bx %
bx 2
bx I
bx w
b1 '
b1 6
b1 0"
b110001100 }
06"
0&"
1(
#80000
b1 +
b1001 )
0(
#85000
b1 U
b1 r
b1 @"
b1 ?"
0?
b0 i
1F
b1 A"
b100000000100 g
b0 D"
b1 B"
b1 C"
b0 s
b1 M
b1 :"
b1 ="
1=
b0 j
b101 P
b0 R
b0 l
b101 Z
b0 Y
b0 J"
b0 h
0<
b1 T
b1 H"
b0 K
b0 X
b0 n
b100001000000000000 L
b100001000000000000 ;"
b100001000000000000 >"
b101 q
b10100000000001010010011 "
b10100000000001010010011 4
b10100000000001010010011 B
b101 3
b0 e
b0 b
b0 S
b0 E"
b0 m
b0 c
b0 [
1t
0o
b110011 `
b1 1"
b1 }
b1010011 -"
16"
b100 ,"
b100 G"
05"
b0 '
b0 6
b0 0"
b100001000000000000 !"
b1 ~
b1 <"
b0 3"
b100 2"
b10000 *"
b0 /"
b1 ."
b101000 )"
b100000011100 ^
b11000 ]
b10100 #
b10100 '"
b110011 ""
1(
#90000
b1010 )
0(
#95000
b0 U
b101 i
b0 r
b0 @"
bx J
bx V
b110010000 g
b0 ?"
bx W
bx I"
b100000000100 h
b1100 j
b1 R
b10 l
b10000 Z
b100011 _
b0 B"
b0 C"
b0 A"
b0 M
b0 :"
b0 ="
b100000000100 e
b10100000000 b
b101 f
b101 Q
b101 F"
b101 c
b101 [
0t
1d
b10011 `
b110 q
b11000010100001010100000100011 "
b11000010100001010100000100011 4
b11000010100001010100000100011 B
b110 3
b0 L
b0 ;"
b0 >"
b1 n
b0 T
b0 H"
b10100000000001010010011 ""
b110101100 ^
b11100 ]
b11000 #
b11000 '"
b11000 )"
b0 !"
14"
1v
b0 ~
b0 <"
b0 2"
b0 *"
b0 ."
b10000 +"
b0 %
b0 2
b0 I
b0 w
b1 '
b1 6
b1 0"
b0 1"
b0 }
06"
1(
#100000
b1011 )
0(
#105000
b101 U
b101 r
b101 @"
b101 ?"
b1011100 g
b110010000 i
b110001100 K
b110001100 X
15
0F
b101 D"
b1 B"
b1 C"
bx s
b10 j
b0 P
b0 l
b11100 Z
1\
b1100011 _
b110001100 Y
b110001100 J"
b110010000 h
1H
b1 T
b1 H"
b0 n
b101 L
b101 ;"
b101 >"
b111 q
b100000000001000111001100011 "
b100000000001000111001100011 4
b100000000001000111001100011 B
b111 3
b1010100110000100 e
b11000010100001010 b
b110000101 f
b1100 k
b1 S
b1 E"
b10 m
b110010000 c
b10000 [
0d
b100011 `
b1 1"
b1 }
b10000 ,"
b10000 G"
15"
b0 +"
b0 '
b0 6
b0 0"
b101 !"
0v
b101 3"
b101 *"
bx /"
b11100 )"
b1111100 ^
b100000 ]
b11100 #
b11100 '"
b11000010100001010100000100011 ""
1(
